ai_mock-0.3.1.dist-info/METADATA
ai_mock-0.3.1.dist-info/WHEEL
ai_mock-0.3.1.dist-info/entry_points.txt
mockai/__init__.py
mockai/anthropic/__init__.py
mockai/anthropic/models.py
mockai/anthropic/router.py
mockai/anthropic/services.py
mockai/cli.py
mockai/constants.py
mockai/dependencies.py
mockai/models/__init__.py
mockai/models/common.py
mockai/models/json_file.py
mockai/openai/__init__.py
mockai/openai/models.py
mockai/openai/router.py
mockai/openai/services.py
mockai/server.py
ai_mock-0.3.1.dist-info/RECORD
