Metadata-Version: 2.1
Name: ai-mock
Version: 0.3.1
Summary: Mock clients for your favorite LLM APIs
Author-Email: Anibal Angulo <ajcardoza2000@gmail.com>
License: MIT
Requires-Python: <4.0,>=3.10
Requires-Dist: aiofiles<25.0.0,>=24.1.0
Requires-Dist: fastapi[standard]<1.0.0,>=0.115.6
Requires-Dist: starlette-compress<2.0.0,>=1.4.0
Requires-Dist: orjson<4.0.0,>=3.10.14
Provides-Extra: openai
Requires-Dist: openai<2.0.0,>=1.59.6; extra == "openai"
Provides-Extra: anthropic
Requires-Dist: anthropic<1.0.0,>=0.42.0; extra == "anthropic"
Provides-Extra: mistralai
Requires-Dist: mistralai<2.0.0,>=1.2.6; extra == "mistralai"
Provides-Extra: cohere
Requires-Dist: cohere<6.0.0,>=5.13.6; extra == "cohere"
